strongtyping/__init__.py
strongtyping/_utils.py
strongtyping/cached_dict.py
strongtyping/cached_set.py
strongtyping/config.py
strongtyping/docs_from_typing.py
strongtyping/docstring_typing.py
strongtyping/helpers.py
strongtyping/strong_typing.py
strongtyping/strong_typing_utils.py
strongtyping/type_namedtuple.py
strongtyping/types.py
strongtyping-stubs/__init__.pyi
strongtyping-stubs/_utils.pyi
strongtyping-stubs/cached_dict.pyi
strongtyping-stubs/cached_set.pyi
strongtyping-stubs/config.pyi
strongtyping-stubs/docs_from_typing.pyi
strongtyping-stubs/docstring_typing.pyi
strongtyping-stubs/strong_typing.pyi
strongtyping-stubs/strong_typing_utils.pyi
strongtyping-stubs/type_namedtuple.pyi
strongtyping-stubs/types.pyi
strongtyping-3.13.4.dist-info/METADATA
strongtyping-3.13.4.dist-info/WHEEL
strongtyping-3.13.4.dist-info/top_level.txt
strongtyping-3.13.4.dist-info/RECORD
