Metadata-Version: 2.4
Name: strongtyping
Version: 3.13.4
Summary: Decorator which checks whether the function is called with the correct type of parameters
Author-email: FelixTheC <fberndt87@gmail.com>
License: MIT License
Project-URL: Homepage, https://github.com/FelixTheC/strongtyping
Project-URL: Repository, https://github.com/FelixTheC/strongtyping
Project-URL: Documentation, https://strongtyping.readthedocs.io/en/latest/
Classifier: License :: OSI Approved :: MIT License
Classifier: Programming Language :: Python :: 3.13
Requires-Python: >=3.13
